pypbem/__init__.py
pypbem/utils/__init__.py
pypbem/utils/threeD/BSLO.py
pypbem/utils/threeD/RHS.py
pypbem/utils/threeD/__init__.py
pypbem/utils/threeD/green_evaluation.py
pypbem/utils/threeD/potential.py
pypbem/utils/threeD/sphere_grid.py
pypbem/utils/twoD/BSLO.py
pypbem/utils/twoD/RHS.py
pypbem/utils/twoD/__init__.py
pypbem/utils/twoD/circle_grid.py
pypbem/utils/twoD/green_evaluation.py
pypbem/utils/twoD/potential.py
pypbem-1.1.0.dist-info/METADATA
pypbem-1.1.0.dist-info/WHEEL
pypbem-1.1.0.dist-info/RECORD
